promptip/__init__.py
promptip/promptip.py
promptip-0.0.1.dist-info/LICENSE
promptip-0.0.1.dist-info/METADATA
promptip-0.0.1.dist-info/WHEEL
promptip-0.0.1.dist-info/entry_points.txt
promptip-0.0.1.dist-info/top_level.txt
promptip-0.0.1.dist-info/RECORD
