Metadata-Version: 2.1
Name: promptip
Version: 0.0.1
Summary: Command-line tool to fine-tune prompts for optimal use with GPT-3.5 and GPT-4.
Home-page: https://github.com/josenerydev/promptip
Author: José Nery
Author-email: josenerydev@gmail.com
Classifier: Development Status :: 3 - Alpha
Classifier: Intended Audience :: Developers
Classifier: License :: OSI Approved :: MIT License
Classifier: Programming Language :: Python :: 3
Classifier: Programming Language :: Python :: 3.6
Classifier: Programming Language :: Python :: 3.7
Classifier: Programming Language :: Python :: 3.8
Classifier: Programming Language :: Python :: 3.9
License-File: LICENSE
Requires-Dist: pathspec
